{
  "name": "bau_macc-ind-elc-100pc",
  "data": [
    {
      "seriesName": "DMD_TRA-P-ACTIVE",
      "seriesValues": [
        [
          2018,
          5.502380100767141
        ],
        [
          2019,
          5.623278614438979
        ],
        [
          2020,
          4.06776832484296
        ],
        [
          2021,
          5.130411047069121
        ],
        [
          2022,
          5.313447410940224
        ],
        [
          2023,
          5.332802500446235
        ],
        [
          2024,
          5.399462531404446
        ],
        [
          2025,
          5.466955812147443
        ],
        [
          2026,
          5.535292773834477
        ],
        [
          2027,
          5.604483932732668
        ],
        [
          2028,
          5.674539981104316
        ],
        [
          2029,
          5.74547173007171
        ],
        [
          2030,
          5.817290125920206
        ],
        [
          2031,
          5.8900062517341105
        ],
        [
          2032,
          5.963631329423182
        ],
        [
          2033,
          6.038176720257032
        ],
        [
          2034,
          6.113653928488816
        ],
        [
          2035,
          6.190074601820684
        ],
        [
          2036,
          6.267450533602414
        ],
        [
          2037,
          6.345793664457828
        ],
        [
          2038,
          6.425116084514837
        ],
        [
          2039,
          6.505430034776275
        ],
        [
          2040,
          6.586747900286266
        ],
        [
          2041,
          6.669082248415345
        ],
        [
          2042,
          6.752445775797679
        ],
        [
          2043,
          6.836851347303893
        ],
        [
          2044,
          6.922311988460783
        ],
        [
          2045,
          7.008840887647549
        ],
        [
          2046,
          7.09645139811116
        ],
        [
          2047,
          7.18515703986757
        ],
        [
          2048,
          7.27497150220995
        ],
        [
          2049,
          7.36590864529785
        ],
        [
          2050,
          7.45798250269719
        ],
        [
          2051,
          7.60757906474118
        ]
      ]
    },
    {
      "seriesName": "DMD_TRA-P-BUS",
      "seriesValues": [
        [
          2018,
          1.20074238891737
        ],
        [
          2019,
          1.234741094251544
        ],
        [
          2020,
          0.8931872470857556
        ],
        [
          2021,
          1.1265188486387772
        ],
        [
          2022,
          1.1667093801219248
        ],
        [
          2023,
          1.170959305980501
        ],
        [
          2024,
          1.1855962977024501
        ],
        [
          2025,
          1.200416251812443
        ],
        [
          2026,
          1.2154214544741764
        ],
        [
          2027,
          1.230614222068128
        ],
        [
          2028,
          1.2459968986051169
        ],
        [
          2029,
          1.2615718593764231
        ],
        [
          2030,
          1.2773415073386423
        ],
        [
          2031,
          1.2933082757607846
        ],
        [
          2032,
          1.3094746293962884
        ],
        [
          2033,
          1.3258430761724946
        ],
        [
          2034,
          1.3424161140712756
        ],
        [
          2035,
          1.3591963148047461
        ],
        [
          2036,
          1.3761862684019426
        ],
        [
          2037,
          1.3933885961798747
        ],
        [
          2038,
          1.4108059531823496
        ],
        [
          2039,
          1.4284410197271917
        ],
        [
          2040,
          1.4462964964427498
        ],
        [
          2041,
          1.4643752024889256
        ],
        [
          2042,
          1.4826798923438298
        ],
        [
          2043,
          1.5012133908243204
        ],
        [
          2044,
          1.5199785580652396
        ],
        [
          2045,
          1.5389782898829605
        ],
        [
          2046,
          1.5582155183658626
        ],
        [
          2047,
          1.5776932121849698
        ],
        [
          2048,
          1.5974143771795837
        ],
        [
          2049,
          1.6173820567374133
        ],
        [
          2050,
          1.6375993322638136
        ],
        [
          2051,
          1.6704473109390112
        ]
      ]
    },
    {
      "seriesName": "DMD_TRA-P-CAR",
      "seriesValues": [
        [
          2018,
          7.486899505665323
        ],
        [
          2019,
          7.632999199820345
        ],
        [
          2020,
          5.517314309823992
        ],
        [
          2021,
          6.963571699507142
        ],
        [
          2022,
          7.225840617664795
        ],
        [
          2023,
          7.261760840479333
        ],
        [
          2024,
          7.3326485581188265
        ],
        [
          2025,
          7.424980892779488
        ],
        [
          2026,
          7.518585439962095
        ],
        [
          2027,
          7.613587068607046
        ],
        [
          2028,
          7.71027375390118
        ],
        [
          2029,
          7.80903949094765
        ],
        [
          2030,
          7.910163719951224
        ],
        [
          2031,
          8.009161901043893
        ],
        [
          2032,
          8.109276408781714
        ],
        [
          2033,
          8.210642348422175
        ],
        [
          2034,
          8.313275377283084
        ],
        [
          2035,
          8.417191317390778
        ],
        [
          2036,
          8.522406204339637
        ],
        [
          2037,
          8.628936277207412
        ],
        [
          2038,
          8.73679796493399
        ],
        [
          2039,
          8.84600792129806
        ],
        [
          2040,
          8.956583045879462
        ],
        [
          2041,
          9.068540332075287
        ],
        [
          2042,
          9.181897083298407
        ],
        [
          2043,
          9.296670793032924
        ],
        [
          2044,
          9.412879180764303
        ],
        [
          2045,
          9.530540174758423
        ],
        [
          2046,
          9.649671925336927
        ],
        [
          2047,
          9.770292799736676
        ],
        [
          2048,
          9.892421485875927
        ],
        [
          2049,
          10.016076742818106
        ],
        [
          2050,
          10.141277673399212
        ],
        [
          2051,
          10.34469737127308
        ]
      ]
    },
    {
      "seriesName": "DMD_TRA-P-LPT",
      "seriesValues": [
        [
          2018,
          0.109203672371144
        ],
        [
          2019,
          0.1190111958081097
        ],
        [
          2020,
          0.0860903425469383
        ],
        [
          2021,
          0.1085801482227461
        ],
        [
          2022,
          0.1124539335049404
        ],
        [
          2023,
          0.112863565024
        ],
        [
          2024,
          0.114274359770197
        ],
        [
          2025,
          0.1157027886582678
        ],
        [
          2026,
          0.1171490732143188
        ],
        [
          2027,
          0.1186134363270962
        ],
        [
          2028,
          0.1200961039752988
        ],
        [
          2029,
          0.12159730496636859
        ],
        [
          2030,
          0.1231172709725516
        ],
        [
          2031,
          0.1246562366299648
        ],
        [
          2032,
          0.1262144398907202
        ],
        [
          2033,
          0.1277921201150273
        ],
        [
          2034,
          0.1293895213488634
        ],
        [
          2035,
          0.1310068901007047
        ],
        [
          2036,
          0.1326444759580545
        ],
        [
          2037,
          0.1343025316329813
        ],
        [
          2038,
          0.1359813130048097
        ],
        [
          2039,
          0.137681079139562
        ],
        [
          2040,
          0.1394020924615929
        ],
        [
          2041,
          0.1411446183357438
        ],
        [
          2042,
          0.1429089257508524
        ],
        [
          2043,
          0.1446952870201844
        ],
        [
          2044,
          0.14650397781789168
        ],
        [
          2045,
          0.1483352772566524
        ],
        [
          2046,
          0.150189467961646
        ],
        [
          2047,
          0.15206683602530302
        ],
        [
          2048,
          0.153967663873835
        ],
        [
          2049,
          0.155892259467313
        ],
        [
          2050,
          0.15784091253195
        ],
        [
          2051,
          0.161006969953259
        ]
      ]
    },
    {
      "seriesName": "DMD_TRA-P-MOT",
      "seriesValues": [
        [
          2018,
          0.0182854287863667
        ],
        [
          2019,
          0.0185494736972138
        ],
        [
          2020,
          0.0139896593487999
        ],
        [
          2021,
          0.0127014745844534
        ],
        [
          2022,
          0.01103290549387
        ],
        [
          2023,
          0.0099761698359812
        ],
        [
          2024,
          0.0094777499219363
        ],
        [
          2025,
          0.0089220083098577
        ],
        [
          2026,
          0.0082411991466993
        ],
        [
          2027,
          0.0073249464717705
        ],
        [
          2028,
          0.0058996587185721
        ],
        [
          2029,
          0.0035860956384105
        ],
        [
          2030,
          0.0001196426610678
        ]
      ]
    },
    {
      "seriesName": "DMD_TRA-P-TAXI",
      "seriesValues": [
        [
          2018,
          0.2390500129532707
        ],
        [
          2019,
          0.24781888327235077
        ],
        [
          2020,
          0.1829419603286338
        ],
        [
          2021,
          0.23073276920942698
        ],
        [
          2022,
          0.22725492749649467
        ],
        [
          2023,
          0.21958077544596522
        ],
        [
          2024,
          0.2428329867930826
        ],
        [
          2025,
          0.24586840607715627
        ],
        [
          2026,
          0.24894176037229815
        ],
        [
          2027,
          0.2520535316418531
        ],
        [
          2028,
          0.255204199643877
        ],
        [
          2029,
          0.25839425056655513
        ],
        [
          2030,
          0.2616241745141539
        ],
        [
          2031,
          0.2648944800443532
        ],
        [
          2032,
          0.26820566506453936
        ],
        [
          2033,
          0.27155824045201377
        ],
        [
          2034,
          0.27495271653162756
        ],
        [
          2035,
          0.27838962362959596
        ],
        [
          2036,
          0.2818694927844624
        ],
        [
          2037,
          0.2853928535659139
        ],
        [
          2038,
          0.2889602628063034
        ],
        [
          2039,
          0.2925722163027139
        ],
        [
          2040,
          0.29622938895294104
        ],
        [
          2041,
          0.299932255460644
        ],
        [
          2042,
          0.3036814078287
        ],
        [
          2043,
          0.30747742465224404
        ],
        [
          2044,
          0.311320891546837
        ],
        [
          2045,
          0.3152124124507166
        ],
        [
          2046,
          0.31915256733909225
        ],
        [
          2047,
          0.3231419739269261
        ],
        [
          2048,
          0.327181238839902
        ],
        [
          2049,
          0.3312710127317149
        ],
        [
          2050,
          0.3354118965938434
        ],
        [
          2051,
          0.34213985552513926
        ]
      ]
    }
  ]
}