{
  "name": "bau_macc-tra-wem-car_bev",
  "data": [
    {
      "seriesName": "DMD_TRA-P-CAR-BEV",
      "seriesValues": [
        [
          2018,
          4.53
        ],
        [
          2019,
          7.973000000000001
        ],
        [
          2020,
          11.913
        ],
        [
          2021,
          20.38189811324817
        ],
        [
          2022,
          35.75784545228388
        ],
        [
          2023,
          58.06371214084701
        ],
        [
          2024,
          75.02853553788695
        ],
        [
          2025,
          97.87591030864318
        ],
        [
          2026,
          135.52250903447836
        ],
        [
          2027,
          171.83302180879753
        ],
        [
          2028,
          215.94521127892156
        ],
        [
          2029,
          269.1216077818494
        ],
        [
          2030,
          333.25800283350264
        ],
        [
          2031,
          405.00587495052184
        ],
        [
          2032,
          484.90614627529027
        ],
        [
          2033,
          573.8933513388988
        ],
        [
          2034,
          672.0099564381438
        ],
        [
          2035,
          803.3047533286818
        ],
        [
          2036,
          934.2333254808692
        ],
        [
          2037,
          1062.7051254075338
        ],
        [
          2038,
          1188.7686127170236
        ],
        [
          2039,
          1327.9586193376315
        ],
        [
          2040,
          1470.1261537002288
        ],
        [
          2041,
          1470.1261538040362
        ],
        [
          2042,
          1470.1261539057048
        ],
        [
          2043,
          1470.1261540110909
        ],
        [
          2044,
          1470.1261541084573
        ],
        [
          2045,
          1470.126154200614
        ],
        [
          2046,
          1470.1261542910943
        ],
        [
          2047,
          1470.1261543598334
        ],
        [
          2048,
          1470.126154422122
        ],
        [
          2049,
          1470.1261544822282
        ],
        [
          2050,
          1470.126154542037
        ],
        [
          2051,
          1470.126154734221
        ]
      ]
    },
    {
      "seriesName": "DMD_TRA-P-CAR-HEV",
      "seriesValues": [
        [
          2018,
          30.573
        ],
        [
          2019,
          41.473
        ],
        [
          2020,
          54.127
        ],
        [
          2021,
          79.21364680272323
        ],
        [
          2022,
          105.98787682399005
        ],
        [
          2023,
          129.9596031667916
        ],
        [
          2024,
          154.69961776771174
        ],
        [
          2025,
          181.45673343225977
        ],
        [
          2026,
          177.12681102426257
        ],
        [
          2027,
          172.13118503688557
        ],
        [
          2028,
          165.98950410610794
        ],
        [
          2029,
          158.53887100211665
        ],
        [
          2030,
          151.6190099425736
        ],
        [
          2031,
          144.94498152017997
        ],
        [
          2032,
          136.38085924527203
        ],
        [
          2033,
          128.10553375684378
        ],
        [
          2034,
          119.59636940969676
        ],
        [
          2035,
          112.09703131801705
        ],
        [
          2036,
          104.23701867557557
        ],
        [
          2037,
          96.82372128098739
        ],
        [
          2038,
          88.28488959431766
        ],
        [
          2039,
          81.15527426119846
        ],
        [
          2040,
          74.71717915537107
        ],
        [
          2041,
          69.72302746345187
        ],
        [
          2042,
          64.74243336839506
        ],
        [
          2043,
          63.749185390194924
        ],
        [
          2044,
          59.012681441260284
        ],
        [
          2045,
          53.949856205608484
        ],
        [
          2046,
          43.68297155474208
        ],
        [
          2047,
          32.73832288070568
        ],
        [
          2048,
          22.61827376496538
        ],
        [
          2049,
          11.879674956296418
        ],
        [
          2051,
          3.2254029968275503e-06
        ]
      ]
    },
    {
      "seriesName": "DMD_TRA-P-CAR-ICE",
      "seriesValues": [
        [
          2018,
          2084.86
        ],
        [
          2019,
          2210.2815
        ],
        [
          2020,
          2304.456
        ],
        [
          2021,
          2254.37330634134
        ],
        [
          2022,
          2229.86366673434
        ],
        [
          2023,
          2210.5158384374317
        ],
        [
          2024,
          2186.1651877683457
        ],
        [
          2025,
          2155.9103819473276
        ],
        [
          2026,
          2117.638997356064
        ],
        [
          2027,
          2083.168639010435
        ],
        [
          2028,
          2047.731964008488
        ],
        [
          2029,
          1993.8249499732785
        ],
        [
          2030,
          1892.6354819278604
        ],
        [
          2031,
          1719.1316457956361
        ],
        [
          2032,
          1608.6850004735988
        ],
        [
          2033,
          1597.8387532392435
        ],
        [
          2034,
          1575.8169845184975
        ],
        [
          2035,
          1511.4060564326078
        ],
        [
          2036,
          1437.9445413802248
        ],
        [
          2037,
          1361.5080922820594
        ],
        [
          2038,
          1289.956419690689
        ],
        [
          2039,
          1233.8872665346219
        ],
        [
          2040,
          1189.3145030119642
        ],
        [
          2041,
          1175.4047934850112
        ],
        [
          2042,
          1232.785691279549
        ],
        [
          2043,
          1284.7121662670284
        ],
        [
          2044,
          1341.0262087430906
        ],
        [
          2045,
          1398.429767700414
        ],
        [
          2046,
          1462.0610053178266
        ],
        [
          2047,
          1527.415099337092
        ],
        [
          2048,
          1597.1654449197815
        ],
        [
          2049,
          1669.4864323357135
        ],
        [
          2050,
          1746.6199433540796
        ],
        [
          2051,
          1785.9961200546818
        ]
      ]
    },
    {
      "seriesName": "DMD_TRA-P-CAR-PHEV",
      "seriesValues": [
        [
          2018,
          2.759
        ],
        [
          2019,
          2.7715
        ],
        [
          2020,
          2.784
        ],
        [
          2021,
          2.7316989729101353
        ],
        [
          2022,
          2.678813628953268
        ],
        [
          2023,
          12.992105873879781
        ],
        [
          2024,
          25.440415383741055
        ],
        [
          2025,
          44.26886182559743
        ],
        [
          2026,
          44.13772515129127
        ],
        [
          2027,
          43.43865744471815
        ],
        [
          2028,
          42.177334992694675
        ],
        [
          2029,
          40.56362759750765
        ],
        [
          2030,
          39.187790247205115
        ],
        [
          2031,
          38.11229443642777
        ],
        [
          2032,
          36.13654913349391
        ],
        [
          2033,
          34.43725689110236
        ],
        [
          2034,
          33.057760476614966
        ],
        [
          2035,
          31.906084852613954
        ],
        [
          2036,
          30.46732750464783
        ],
        [
          2037,
          28.91850809556
        ],
        [
          2038,
          26.747173027243473
        ],
        [
          2039,
          25.423550373383378
        ],
        [
          2040,
          22.77325848799195
        ],
        [
          2041,
          20.563114591018852
        ],
        [
          2042,
          17.560563836060997
        ],
        [
          2043,
          16.985068651185173
        ],
        [
          2044,
          16.745652553577777
        ],
        [
          2045,
          16.745652553577777
        ],
        [
          2046,
          16.745652553577777
        ],
        [
          2047,
          16.745652553577777
        ],
        [
          2048,
          12.591847306498776
        ],
        [
          2049,
          7.57543330265785
        ],
        [
          2051,
          7.832408168435064e-05
        ]
      ]
    },
    {
      "seriesName": "DMD_TRA-P-CAR-FCV",
      "seriesValues": [
        [
          2034,
          0.0
        ],
        [
          2035,
          0.0
        ],
        [
          2036,
          0.0
        ],
        [
          2037,
          0.0
        ],
        [
          2038,
          0.0
        ],
        [
          2039,
          0.0
        ],
        [
          2040,
          0.0
        ],
        [
          2041,
          0.0
        ],
        [
          2042,
          0.0
        ],
        [
          2043,
          0.0
        ],
        [
          2044,
          0.0
        ],
        [
          2045,
          0.0
        ],
        [
          2046,
          0.0
        ],
        [
          2047,
          0.0
        ],
        [
          2048,
          2.93492563056241e-06
        ],
        [
          2049,
          5.70731143140289e-06
        ],
        [
          2050,
          7.13560705215472e-06
        ],
        [
          2051,
          7.54473293349755e-06
        ]
      ]
    }
  ]
}