{
  "name": "bau_macc-tra-100pc-car_bev",
  "data": [
    {
      "seriesName": "FT_AGR",
      "seriesValues": [
        [
          2018,
          10.828838398833572
        ],
        [
          2019,
          10.715624014521573
        ],
        [
          2020,
          10.814604148474118
        ],
        [
          2021,
          10.642436104058586
        ],
        [
          2022,
          14.000000587219253
        ],
        [
          2023,
          10.572490402407361
        ],
        [
          2024,
          10.53284392271004
        ],
        [
          2025,
          10.493292646367067
        ],
        [
          2026,
          10.464723851321917
        ],
        [
          2027,
          10.437358378351378
        ],
        [
          2028,
          10.416639291351078
        ],
        [
          2029,
          10.388092132221171
        ],
        [
          2030,
          10.359559333829738
        ],
        [
          2031,
          10.342594238725084
        ],
        [
          2032,
          10.32555847099576
        ],
        [
          2033,
          10.308450847027759
        ],
        [
          2034,
          10.29127022707488
        ],
        [
          2035,
          10.274015490074001
        ],
        [
          2036,
          10.31534192652058
        ],
        [
          2037,
          10.396578891141179
        ],
        [
          2038,
          10.362943902373988
        ],
        [
          2039,
          10.432533419297082
        ],
        [
          2040,
          10.398593806248446
        ],
        [
          2041,
          10.364811810463735
        ],
        [
          2042,
          10.331048615229353
        ],
        [
          2043,
          10.297303450423389
        ],
        [
          2044,
          10.263575565315747
        ],
        [
          2045,
          10.22986419187089
        ],
        [
          2046,
          10.196900992241035
        ],
        [
          2047,
          10.163936287215156
        ],
        [
          2048,
          10.130969691660809
        ],
        [
          2049,
          10.098000832149785
        ],
        [
          2050,
          10.065029366271586
        ],
        [
          2051,
          10.06502937669248
        ]
      ]
    },
    {
      "seriesName": "FT_IND",
      "seriesValues": [
        [
          2018,
          93.60078787196895
        ],
        [
          2019,
          90.79626934180521
        ],
        [
          2020,
          99.57603763179887
        ],
        [
          2021,
          98.2730162989975
        ],
        [
          2022,
          99.10125673034526
        ],
        [
          2023,
          98.35011242365746
        ],
        [
          2024,
          98.79121789828214
        ],
        [
          2025,
          99.89068915089439
        ],
        [
          2026,
          98.69109188116528
        ],
        [
          2027,
          94.7095939074326
        ],
        [
          2028,
          90.33976500718056
        ],
        [
          2029,
          88.09317626946108
        ],
        [
          2030,
          85.91074882571131
        ],
        [
          2031,
          83.78432380611744
        ],
        [
          2032,
          81.86786069932847
        ],
        [
          2033,
          80.34615384361075
        ],
        [
          2034,
          79.47621846686692
        ],
        [
          2035,
          78.63932519822795
        ],
        [
          2036,
          77.83045129142023
        ],
        [
          2037,
          77.70964981537743
        ],
        [
          2038,
          81.16769895947972
        ],
        [
          2039,
          80.76679446739509
        ],
        [
          2040,
          79.94639559777163
        ],
        [
          2041,
          78.97498362828416
        ],
        [
          2042,
          78.184021674676
        ],
        [
          2043,
          77.27226580486699
        ],
        [
          2044,
          77.04752438476596
        ],
        [
          2045,
          76.45837633814291
        ],
        [
          2046,
          75.6344068059861
        ],
        [
          2047,
          74.83361854046613
        ],
        [
          2048,
          74.18509117167208
        ],
        [
          2049,
          73.83268990521083
        ],
        [
          2050,
          73.13687193528595
        ],
        [
          2051,
          72.69322101795542
        ]
      ]
    },
    {
      "seriesName": "FT_RSD",
      "seriesValues": [
        [
          2018,
          126.06209393183664
        ],
        [
          2019,
          125.88774084041985
        ],
        [
          2020,
          133.40389050022023
        ],
        [
          2021,
          128.20993136141252
        ],
        [
          2022,
          122.57348858991514
        ],
        [
          2023,
          120.64961296542006
        ],
        [
          2024,
          121.00701472210405
        ],
        [
          2025,
          117.38961418102865
        ],
        [
          2026,
          116.14767445779805
        ],
        [
          2027,
          115.69202634339591
        ],
        [
          2028,
          115.24448194061458
        ],
        [
          2029,
          114.99357486152822
        ],
        [
          2030,
          115.20620282370876
        ],
        [
          2031,
          115.3461903096348
        ],
        [
          2032,
          115.19143312341521
        ],
        [
          2033,
          115.03746209777417
        ],
        [
          2034,
          114.92678309382951
        ],
        [
          2035,
          115.02626236281519
        ],
        [
          2036,
          115.10973969055559
        ],
        [
          2037,
          115.21006245634838
        ],
        [
          2038,
          115.41863758626755
        ],
        [
          2039,
          117.30094730121215
        ],
        [
          2040,
          117.27817015081222
        ],
        [
          2041,
          116.95162150816171
        ],
        [
          2042,
          116.84187479733642
        ],
        [
          2043,
          116.77903905661638
        ],
        [
          2044,
          116.71196086217157
        ],
        [
          2045,
          116.6344739091332
        ],
        [
          2046,
          116.54612089530372
        ],
        [
          2047,
          116.53336411959792
        ],
        [
          2048,
          116.51482376825739
        ],
        [
          2049,
          116.48499479569064
        ],
        [
          2050,
          116.43983576385553
        ],
        [
          2051,
          115.28708210678292
        ]
      ]
    },
    {
      "seriesName": "FT_SRV",
      "seriesValues": [
        [
          2018,
          70.73449124839344
        ],
        [
          2019,
          72.04043950027294
        ],
        [
          2020,
          70.90765446472547
        ],
        [
          2021,
          76.57158480763437
        ],
        [
          2022,
          82.80015451353067
        ],
        [
          2023,
          87.74680132597547
        ],
        [
          2024,
          92.6945760122484
        ],
        [
          2025,
          100.19587925602139
        ],
        [
          2026,
          106.96274336685885
        ],
        [
          2027,
          112.4093823307339
        ],
        [
          2028,
          117.37727708150315
        ],
        [
          2029,
          122.47724965576876
        ],
        [
          2030,
          127.3579463234928
        ],
        [
          2031,
          132.38222090438296
        ],
        [
          2032,
          131.71196376896393
        ],
        [
          2033,
          132.69618811179225
        ],
        [
          2034,
          133.55288180112922
        ],
        [
          2035,
          134.5359960555827
        ],
        [
          2036,
          135.04768583829065
        ],
        [
          2037,
          135.94045496757943
        ],
        [
          2038,
          136.70629390662708
        ],
        [
          2039,
          136.25413441421372
        ],
        [
          2040,
          135.68747034960472
        ],
        [
          2041,
          137.12412875070973
        ],
        [
          2042,
          140.50252066905236
        ],
        [
          2043,
          141.70298014547438
        ],
        [
          2044,
          142.39657087561204
        ],
        [
          2045,
          143.10416160533558
        ],
        [
          2046,
          143.2398460605221
        ],
        [
          2047,
          143.84603298456648
        ],
        [
          2048,
          144.50614076316398
        ],
        [
          2049,
          144.89903407581403
        ],
        [
          2050,
          144.82321237362052
        ],
        [
          2051,
          145.0051898498996
        ]
      ]
    },
    {
      "seriesName": "FT_TRA",
      "seriesValues": [
        [
          2018,
          237.81754366098758
        ],
        [
          2019,
          232.56783370791797
        ],
        [
          2020,
          173.33102334858253
        ],
        [
          2021,
          184.48044826923137
        ],
        [
          2022,
          217.28995296222072
        ],
        [
          2023,
          225.03730329517464
        ],
        [
          2024,
          235.4489765891684
        ],
        [
          2025,
          234.9909011621591
        ],
        [
          2026,
          232.78587908618283
        ],
        [
          2027,
          230.3468519281658
        ],
        [
          2028,
          229.76464342146863
        ],
        [
          2029,
          227.0293722379042
        ],
        [
          2030,
          220.6781693098673
        ],
        [
          2031,
          215.84659968179284
        ],
        [
          2032,
          210.9957004577355
        ],
        [
          2033,
          206.30656524282497
        ],
        [
          2034,
          201.78896032318045
        ],
        [
          2035,
          197.79470132877225
        ],
        [
          2036,
          196.0318599780176
        ],
        [
          2037,
          197.7448829528406
        ],
        [
          2038,
          200.0990299187771
        ],
        [
          2039,
          202.54602581444945
        ],
        [
          2040,
          205.2385443889021
        ],
        [
          2041,
          207.602521714201
        ],
        [
          2042,
          210.0551155460347
        ],
        [
          2043,
          212.5360873116124
        ],
        [
          2044,
          214.98554569503546
        ],
        [
          2045,
          217.58599700166175
        ],
        [
          2046,
          220.30202907308694
        ],
        [
          2047,
          222.92859790940554
        ],
        [
          2048,
          225.69643377853893
        ],
        [
          2049,
          228.5218630997239
        ],
        [
          2050,
          231.3137607893663
        ],
        [
          2051,
          234.0309950425344
        ]
      ]
    }
  ]
}