{
  "name": "bau_macc-pow-bioccs",
  "data": [
    {
      "seriesName": "FT_AGR",
      "seriesValues": [
        [
          2018,
          2.099999999655826
        ],
        [
          2019,
          1.9999999997083218
        ],
        [
          2020,
          2.0999999996194125
        ],
        [
          2021,
          1.99999999964271
        ],
        [
          2022,
          1.8999999996642227
        ],
        [
          2023,
          1.968075838935288
        ],
        [
          2024,
          1.9558287042702929
        ],
        [
          2025,
          1.946535238826058
        ],
        [
          2026,
          1.9356170013377871
        ],
        [
          2027,
          1.9239943000825899
        ],
        [
          2028,
          4.273403059091899e-06
        ],
        [
          2029,
          0.0
        ],
        [
          2030,
          0.0
        ],
        [
          2051,
          0.0
        ]
      ]
    },
    {
      "seriesName": "FT_IND",
      "seriesValues": [
        [
          2018,
          23.439361110178357
        ],
        [
          2019,
          23.43936111980406
        ],
        [
          2020,
          23.479709991097987
        ],
        [
          2021,
          23.70419087303778
        ],
        [
          2022,
          28.652639385494727
        ],
        [
          2023,
          24.351664366224163
        ],
        [
          2024,
          26.05628087031285
        ],
        [
          2025,
          26.354800939896545
        ],
        [
          2026,
          27.09910154223542
        ],
        [
          2027,
          23.927237709460318
        ],
        [
          2028,
          23.439361144519747
        ],
        [
          2029,
          22.993875233614386
        ],
        [
          2030,
          22.58578391954042
        ],
        [
          2031,
          22.210196548612206
        ],
        [
          2032,
          21.86468791368231
        ],
        [
          2033,
          21.543563313970996
        ],
        [
          2034,
          21.241455664262908
        ],
        [
          2035,
          20.957981965032353
        ],
        [
          2036,
          20.690240128071547
        ],
        [
          2037,
          20.43804641386899
        ],
        [
          2038,
          20.199385896762955
        ],
        [
          2039,
          19.973027453680373
        ],
        [
          2040,
          19.759714486140606
        ],
        [
          2041,
          19.559502873666155
        ],
        [
          2042,
          19.372536679369055
        ],
        [
          2043,
          19.198723642702227
        ],
        [
          2044,
          19.038914432270897
        ],
        [
          2045,
          18.893389529014623
        ],
        [
          2046,
          18.762062919810813
        ],
        [
          2047,
          18.645459767099737
        ],
        [
          2048,
          18.544407364960858
        ],
        [
          2049,
          18.46093841687174
        ],
        [
          2050,
          18.395430398219716
        ],
        [
          2051,
          18.395430446131275
        ]
      ]
    },
    {
      "seriesName": "FT_RSD",
      "seriesValues": [
        [
          2018,
          28.914604903354903
        ],
        [
          2019,
          30.183999994937142
        ],
        [
          2020,
          30.771999993676054
        ],
        [
          2021,
          31.16399999382328
        ],
        [
          2022,
          31.108473067395348
        ],
        [
          2023,
          34.814381816393634
        ],
        [
          2024,
          35.37957716478293
        ],
        [
          2025,
          35.64372099554867
        ],
        [
          2026,
          35.73290186382723
        ],
        [
          2027,
          35.796648685421964
        ],
        [
          2028,
          35.8494433131387
        ],
        [
          2029,
          35.62619078274027
        ],
        [
          2030,
          35.660571812752515
        ],
        [
          2031,
          36.02409549302622
        ],
        [
          2032,
          36.140974948989154
        ],
        [
          2033,
          35.894468820446804
        ],
        [
          2034,
          36.19209875661234
        ],
        [
          2035,
          36.28990082627309
        ],
        [
          2036,
          36.5618151235381
        ],
        [
          2037,
          36.68810622830868
        ],
        [
          2038,
          36.942368291306366
        ],
        [
          2039,
          37.30461865927629
        ],
        [
          2040,
          37.58930704212449
        ],
        [
          2041,
          37.610822778466925
        ],
        [
          2042,
          37.96379279414749
        ],
        [
          2043,
          38.34550059400144
        ],
        [
          2044,
          38.66148440957206
        ],
        [
          2045,
          39.04706532588938
        ],
        [
          2046,
          39.270342497568926
        ],
        [
          2047,
          39.48644289257241
        ],
        [
          2048,
          39.694872650551766
        ],
        [
          2049,
          39.89069219452271
        ],
        [
          2050,
          40.00875656532646
        ],
        [
          2051,
          41.192360646750814
        ]
      ]
    },
    {
      "seriesName": "FT_SRV",
      "seriesValues": [
        [
          2018,
          45.00367742350402
        ],
        [
          2019,
          46.88593199790649
        ],
        [
          2020,
          45.9379999904491
        ],
        [
          2021,
          50.34509462469103
        ],
        [
          2022,
          55.31099998841395
        ],
        [
          2023,
          64.21900856311323
        ],
        [
          2024,
          67.47789282306816
        ],
        [
          2025,
          70.73943752805613
        ],
        [
          2026,
          73.94369996101133
        ],
        [
          2027,
          76.39841723386252
        ],
        [
          2028,
          79.22686564768686
        ],
        [
          2029,
          81.58049974791822
        ],
        [
          2030,
          83.22014355311245
        ],
        [
          2031,
          87.07886934416524
        ],
        [
          2032,
          85.52869728361958
        ],
        [
          2033,
          85.95526871940609
        ],
        [
          2034,
          86.37419202602405
        ],
        [
          2035,
          86.6806901214363
        ],
        [
          2036,
          87.1066658494042
        ],
        [
          2037,
          87.4269592806731
        ],
        [
          2038,
          87.58989962790129
        ],
        [
          2039,
          86.11604774140294
        ],
        [
          2040,
          85.33281108659237
        ],
        [
          2041,
          85.43963819080281
        ],
        [
          2042,
          83.8450904873274
        ],
        [
          2043,
          84.06005376094834
        ],
        [
          2044,
          84.27605312434109
        ],
        [
          2045,
          84.49302239169114
        ],
        [
          2046,
          84.71043881926585
        ],
        [
          2047,
          84.93779692534181
        ],
        [
          2048,
          85.14024850478096
        ],
        [
          2049,
          84.97240403588444
        ],
        [
          2050,
          85.0310183942092
        ],
        [
          2051,
          86.19652825999083
        ]
      ]
    },
    {
      "seriesName": "FT_TRA",
      "seriesValues": [
        [
          2018,
          0.3848743763492123
        ],
        [
          2019,
          0.5382000026043317
        ],
        [
          2020,
          0.6727500017970468
        ],
        [
          2021,
          0.7452000027922776
        ],
        [
          2022,
          0.7720000029100574
        ],
        [
          2023,
          7.5568865696897864
        ],
        [
          2024,
          6.9541763892244015
        ],
        [
          2025,
          6.689358303347589
        ],
        [
          2026,
          5.871135950148466
        ],
        [
          2027,
          5.078480259084044
        ],
        [
          2028,
          4.187738890463374
        ],
        [
          2029,
          2.7472634967892837
        ],
        [
          2030,
          1.67917986787971
        ],
        [
          2031,
          2.07414050730914
        ],
        [
          2032,
          2.234286398992412
        ],
        [
          2033,
          1.7859363256937342
        ],
        [
          2034,
          1.82369574993281
        ],
        [
          2035,
          1.8636700134240742
        ],
        [
          2036,
          1.9005683655653454
        ],
        [
          2037,
          1.9397122279969843
        ],
        [
          2038,
          1.9729747916810734
        ],
        [
          2039,
          2.0127623562764456
        ],
        [
          2040,
          1.9046672300041037
        ],
        [
          2041,
          1.9552110399308191
        ],
        [
          2042,
          2.0039777177967846
        ],
        [
          2043,
          2.081322203694918
        ],
        [
          2044,
          2.1511951984343596
        ],
        [
          2045,
          2.2203416471449566
        ],
        [
          2046,
          2.279898780784346
        ],
        [
          2047,
          2.316093875419246
        ],
        [
          2048,
          2.3284182903723276
        ],
        [
          2049,
          2.3171136839200264
        ],
        [
          2050,
          2.2857488611149592
        ],
        [
          2051,
          3.0101493802085124
        ]
      ]
    }
  ]
}