{
  "name": "bau_macc-pow-50pc-sol",
  "data": [
    {
      "seriesName": "PWR-GAS",
      "seriesValues": [
        [
          2019,
          0.0
        ],
        [
          2020,
          0.0
        ],
        [
          2021,
          0.0
        ],
        [
          2022,
          0.0
        ],
        [
          2026,
          0.0
        ],
        [
          2027,
          0.0
        ],
        [
          2028,
          1.63244109469388
        ],
        [
          2029,
          0.411421155018409
        ],
        [
          2030,
          0.272328940728828
        ],
        [
          2031,
          0.143859595873302
        ],
        [
          2034,
          0.0044837576830399
        ],
        [
          2035,
          0.0747208283562296
        ],
        [
          2036,
          0.0897446784583423
        ],
        [
          2037,
          0.0449100454329921
        ],
        [
          2038,
          0.0559429016715648
        ],
        [
          2039,
          0.017758124721234
        ],
        [
          2040,
          0.152042171354659
        ],
        [
          2041,
          0.188511614289093
        ],
        [
          2042,
          0.253396945602277
        ],
        [
          2043,
          0.167817659572235
        ],
        [
          2044,
          0.138346579129837
        ],
        [
          2045,
          0.0925970907380669
        ],
        [
          2047,
          0.0501280577524411
        ],
        [
          2048,
          0.0
        ],
        [
          2049,
          0.0
        ],
        [
          2050,
          0.0
        ],
        [
          2051,
          0.0
        ]
      ]
    },
    {
      "seriesName": "PWR-PEA",
      "seriesValues": [
        [
          2019,
          0.0
        ],
        [
          2022,
          0.0247230951743366
        ]
      ]
    },
    {
      "seriesName": "PWR-SOL",
      "seriesValues": [
        [
          2019,
          0.02000000044652688
        ],
        [
          2020,
          0.03300000044830677
        ],
        [
          2021,
          0.2080000001846745
        ],
        [
          2022,
          0.12299999121448432
        ],
        [
          2023,
          0.33199999012405074
        ],
        [
          2024,
          0.23899999210488534
        ],
        [
          2025,
          1.95499999153822
        ],
        [
          2026,
          0.6000054811298434
        ],
        [
          2027,
          0.5999891858407422
        ],
        [
          2028,
          0.6000031510873431
        ],
        [
          2029,
          0.5999951133907473
        ],
        [
          2030,
          0.6000030409690468
        ],
        [
          2031,
          0.20000134512348583
        ],
        [
          2033,
          0.4000049774169275
        ],
        [
          2034,
          0.20000310627395487
        ],
        [
          2035,
          0.20000238808947723
        ],
        [
          2036,
          0.19999981682271456
        ],
        [
          2037,
          0.20000071167312158
        ],
        [
          2038,
          0.2000031926006315
        ],
        [
          2039,
          0.19999680671623726
        ],
        [
          2040,
          0.1999966768249015
        ],
        [
          2044,
          0.019999996631925254
        ],
        [
          2045,
          0.033000019760662566
        ],
        [
          2046,
          0.20800000622484802
        ],
        [
          2047,
          0.12299992211621445
        ],
        [
          2048,
          0.41600026732986994
        ],
        [
          2049,
          1.8000001768375975
        ],
        [
          2050,
          2.399994489440534
        ],
        [
          2051,
          2.399994489432953
        ]
      ]
    },
    {
      "seriesName": "PWR-WIN-ON",
      "seriesValues": [
        [
          2022,
          0.5712896175747777
        ],
        [
          2024,
          0.5730103050522849
        ],
        [
          2051,
          1.2650000090487867
        ]
      ]
    },
    {
      "seriesName": "PWR-MSW",
      "seriesValues": [
        [
          2029,
          0.0959976863634399
        ],
        [
          2030,
          0.0008545767099282
        ],
        [
          2031,
          0.000854577829945
        ],
        [
          2032,
          0.0008545788959511
        ],
        [
          2033,
          0.0008545784470924
        ],
        [
          2034,
          0.0008545777824589
        ],
        [
          2035,
          0.0008545782066283
        ],
        [
          2036,
          0.0008545781959746
        ],
        [
          2037,
          0.0008545781594783
        ],
        [
          2038,
          0.0008545779593956
        ],
        [
          2039,
          0.0008545795930646
        ],
        [
          2040,
          0.0008545782602559
        ],
        [
          2041,
          0.0014242983148933
        ],
        [
          2042,
          0.0014242982373538
        ],
        [
          2043,
          0.0014242983869951
        ],
        [
          2044,
          0.001424313003443
        ],
        [
          2045,
          0.0014242997349742
        ],
        [
          2046,
          0.0014242984709916
        ],
        [
          2047,
          0.0014242985543586
        ],
        [
          2048,
          0.0014242986509052
        ],
        [
          2049,
          0.0014242987305862
        ],
        [
          2050,
          0.0014242989024819
        ]
      ]
    },
    {
      "seriesName": "PWR-GAS-CCS",
      "seriesValues": [
        [
          2030,
          0.0
        ]
      ]
    },
    {
      "seriesName": "PWR-OCE",
      "seriesValues": [
        [
          2035,
          0.0
        ],
        [
          2040,
          0.0
        ],
        [
          2041,
          0.0
        ],
        [
          2042,
          0.0
        ],
        [
          2043,
          0.0
        ],
        [
          2044,
          0.0999999687248765
        ],
        [
          2045,
          0.12000002773092922
        ],
        [
          2046,
          0.14400003139953488
        ],
        [
          2047,
          0.1728000543857631
        ],
        [
          2048,
          0.20736013651031432
        ],
        [
          2049,
          0.20583986256665515
        ],
        [
          2050,
          0.05000009010684038
        ]
      ]
    },
    {
      "seriesName": "PWR-H2",
      "seriesValues": [
        [
          2051,
          0.0
        ]
      ]
    },
    {
      "seriesName": "PWR-WIN-OF",
      "seriesValues": [
        [
          2051,
          2.13499999778435
        ]
      ]
    }
  ]
}