{
  "name": "bau_macc",
  "data": [
    {
      "seriesName": "TRADST",
      "seriesValues": [
        [
          2018,
          57.20963557841085
        ],
        [
          2019,
          56.857328297115146
        ],
        [
          2020,
          55.28110547754691
        ],
        [
          2021,
          56.987559324370196
        ],
        [
          2022,
          58.31244941882314
        ],
        [
          2023,
          67.81780744302259
        ],
        [
          2024,
          79.9327454621217
        ],
        [
          2025,
          82.82154373923301
        ],
        [
          2026,
          85.0882224644096
        ],
        [
          2027,
          87.25141488524545
        ],
        [
          2028,
          89.355289688542
        ],
        [
          2029,
          91.43021853229592
        ],
        [
          2030,
          93.46154910156613
        ],
        [
          2031,
          95.85074396958899
        ],
        [
          2032,
          98.40253489238523
        ],
        [
          2033,
          101.03807989201913
        ],
        [
          2034,
          103.70098024050179
        ],
        [
          2035,
          106.28206949518412
        ],
        [
          2036,
          108.68568968473639
        ],
        [
          2037,
          110.88878466285871
        ],
        [
          2038,
          112.91380232425303
        ],
        [
          2039,
          114.81829764620696
        ],
        [
          2040,
          116.65344119831892
        ],
        [
          2041,
          118.47805125807234
        ],
        [
          2042,
          120.31408603172797
        ],
        [
          2043,
          122.19053954056139
        ],
        [
          2044,
          124.11004020862299
        ],
        [
          2045,
          126.09196292777457
        ],
        [
          2046,
          128.03447660550086
        ],
        [
          2047,
          130.01481078816724
        ],
        [
          2048,
          131.98155397699216
        ],
        [
          2049,
          133.94623643176885
        ],
        [
          2050,
          135.8767553290206
        ],
        [
          2051,
          136.84156332777368
        ]
      ]
    },
    {
      "seriesName": "TRAGSL",
      "seriesValues": [
        [
          2018,
          0.0402508287699681
        ],
        [
          2019,
          0.040250825011081
        ],
        [
          2021,
          0.0389666795711055
        ],
        [
          2022,
          0.0376961378686691
        ],
        [
          2023,
          0.0
        ],
        [
          2024,
          0.0340704656095115
        ],
        [
          2025,
          0.0320774285665703
        ],
        [
          2026,
          0.0302774601518922
        ],
        [
          2027,
          0.0287575237639552
        ],
        [
          2028,
          0.0275392325509917
        ],
        [
          2029,
          0.0263921601142224
        ],
        [
          2030,
          0.0251621437298155
        ],
        [
          2031,
          0.0233156624404805
        ],
        [
          2032,
          0.0206603074391145
        ],
        [
          2033,
          0.0173907174437323
        ],
        [
          2034,
          0.013638091101983
        ],
        [
          2035,
          0.0098420673876671
        ],
        [
          2036,
          0.0065158996194182
        ],
        [
          2037,
          0.0039473023981786
        ],
        [
          2038,
          0.0021834275403384
        ],
        [
          2039,
          0.0011007740795382
        ],
        [
          2040,
          0.0005049347987217
        ],
        [
          2041,
          0.0002103004171332
        ],
        [
          2042,
          7.92316056753427e-05
        ]
      ]
    },
    {
      "seriesName": "TRACNG",
      "seriesValues": [
        [
          2019,
          0.0
        ],
        [
          2020,
          0.0
        ],
        [
          2021,
          0.0
        ],
        [
          2022,
          0.0
        ]
      ]
    },
    {
      "seriesName": "TRAELC",
      "seriesValues": [
        [
          2019,
          0.023236450614078065
        ],
        [
          2020,
          0.03304025073083922
        ],
        [
          2021,
          0.044032453328815654
        ],
        [
          2022,
          0.03806393627665207
        ],
        [
          2023,
          0.05025296092317245
        ],
        [
          2024,
          0.06472057873390977
        ],
        [
          2025,
          0.08899937439730464
        ],
        [
          2026,
          0.0913469475072286
        ],
        [
          2027,
          0.09277945929637818
        ],
        [
          2028,
          0.08887830310752196
        ],
        [
          2029,
          0.08507181305838091
        ],
        [
          2030,
          0.08111997367377198
        ],
        [
          2031,
          0.0771778589855492
        ],
        [
          2032,
          0.07286797131277234
        ],
        [
          2033,
          0.06827493489274122
        ],
        [
          2034,
          0.06374262557002525
        ],
        [
          2035,
          0.05973056043098679
        ],
        [
          2036,
          0.05652281754145254
        ],
        [
          2037,
          0.05372114842222122
        ],
        [
          2038,
          0.05189801593660182
        ],
        [
          2039,
          0.050051728034857114
        ],
        [
          2040,
          0.04853424459608439
        ],
        [
          2041,
          0.04657503100360611
        ],
        [
          2042,
          0.04606639189568053
        ],
        [
          2043,
          0.04405521303551894
        ],
        [
          2044,
          0.04193163335967168
        ],
        [
          2045,
          0.03698020178904246
        ],
        [
          2046,
          0.037812389546718096
        ],
        [
          2047,
          0.038663314398348525
        ],
        [
          2048,
          0.03953371989862246
        ],
        [
          2049,
          0.04042269690826745
        ],
        [
          2050,
          0.041333141229620736
        ],
        [
          2051,
          0.4294609903667556
        ]
      ]
    },
    {
      "seriesName": "TRAH2",
      "seriesValues": [
        [
          2051,
          0.37368395744130334
        ]
      ]
    }
  ]
}