{
  "name": "bau_macc-tra-50pc-bus_bev",
  "data": [
    {
      "seriesName": "SBIORGAS03",
      "seriesValues": [
        [
          2018,
          1.85037120195498
        ],
        [
          2019,
          1.85037120235375
        ],
        [
          2020,
          1.8503712029529
        ],
        [
          2021,
          1.85037120488872
        ],
        [
          2022,
          2.18899999155192
        ],
        [
          2023,
          2.82679998846367
        ],
        [
          2024,
          3.29489551579273
        ],
        [
          2025,
          4.15387459733889
        ],
        [
          2026,
          4.1538746258036
        ],
        [
          2027,
          4.15387463107652
        ],
        [
          2028,
          4.15387468176744
        ],
        [
          2029,
          4.70276062489909
        ],
        [
          2030,
          4.91729322321687
        ],
        [
          2031,
          5.1696160359788
        ],
        [
          2032,
          5.28002190213734
        ],
        [
          2033,
          5.28002194480593
        ],
        [
          2034,
          5.28002195169702
        ],
        [
          2035,
          5.28002195502631
        ],
        [
          2036,
          5.28002195809641
        ],
        [
          2037,
          5.28002196596677
        ],
        [
          2038,
          4.97762895868729
        ],
        [
          2039,
          6.31590278808736
        ],
        [
          2040,
          6.31590279093969
        ],
        [
          2041,
          6.31590279683065
        ],
        [
          2042,
          6.21583385839939
        ],
        [
          2043,
          6.24378470945701
        ],
        [
          2044,
          6.41949867510615
        ],
        [
          2045,
          6.33234908930252
        ],
        [
          2046,
          6.37235840353282
        ],
        [
          2047,
          6.41039121493883
        ],
        [
          2048,
          6.44838837778432
        ],
        [
          2049,
          6.48635006357812
        ],
        [
          2050,
          6.52427651551803
        ],
        [
          2051,
          6.52427637448576
        ]
      ]
    },
    {
      "seriesName": "SBIORGAS06",
      "seriesValues": [
        [
          2023,
          0.0
        ],
        [
          2024,
          0.0
        ],
        [
          2025,
          0.0
        ],
        [
          2026,
          0.0
        ],
        [
          2027,
          0.0
        ],
        [
          2028,
          0.0
        ],
        [
          2029,
          0.0
        ],
        [
          2030,
          0.926019859885994
        ],
        [
          2031,
          1.5100266154645
        ],
        [
          2032,
          1.51002668718642
        ],
        [
          2033,
          1.51002669792806
        ],
        [
          2034,
          1.51002670276791
        ],
        [
          2035,
          1.51002670551348
        ],
        [
          2036,
          1.51002670803761
        ],
        [
          2037,
          1.51002671334253
        ],
        [
          2038,
          1.51002672803107
        ],
        [
          2039,
          1.66928399704182
        ],
        [
          2040,
          1.66928399658366
        ],
        [
          2041,
          1.66928399650543
        ],
        [
          2042,
          1.66928399579617
        ],
        [
          2043,
          1.66928399559017
        ],
        [
          2044,
          1.66928399638768
        ],
        [
          2045,
          1.66928399210517
        ],
        [
          2046,
          1.66928399107802
        ],
        [
          2047,
          1.66928399371591
        ],
        [
          2048,
          1.66928399352159
        ],
        [
          2049,
          1.669283992453
        ],
        [
          2050,
          1.66928399289308
        ],
        [
          2051,
          1.66928399052962
        ]
      ]
    },
    {
      "seriesName": "SBIORGAS01",
      "seriesValues": [
        [
          2039,
          0.0
        ],
        [
          2040,
          0.0
        ],
        [
          2041,
          0.0
        ],
        [
          2042,
          0.0
        ],
        [
          2043,
          0.0
        ],
        [
          2044,
          0.0
        ],
        [
          2045,
          0.0
        ],
        [
          2046,
          0.0
        ],
        [
          2047,
          0.0
        ],
        [
          2048,
          0.0
        ],
        [
          2049,
          0.0
        ],
        [
          2050,
          0.0
        ],
        [
          2051,
          0.0
        ]
      ]
    },
    {
      "seriesName": "SBIORGAS02",
      "seriesValues": [
        [
          2039,
          0.0
        ],
        [
          2040,
          0.0
        ],
        [
          2041,
          0.0
        ],
        [
          2042,
          0.0
        ],
        [
          2043,
          0.0
        ],
        [
          2044,
          0.0
        ],
        [
          2045,
          0.0
        ],
        [
          2046,
          0.0
        ],
        [
          2047,
          0.0
        ],
        [
          2048,
          0.0
        ],
        [
          2049,
          0.0
        ],
        [
          2050,
          0.0
        ],
        [
          2051,
          0.0
        ]
      ]
    }
  ]
}